Metadata-Version: 2.4
Name: ticked
Version: 0.3.6
Summary: A terminal-based task management and productivity tool.
Author-email: Akrm Al-Hakimi <alhakimiakrmj@gmail.com>
License: MIT
Project-URL: Homepage, https://github.com/cachebag/Ticked
Keywords: terminal-ui,task-management,productivity,spotify,vim-like,code-editor,pomodoro,student,STEM,university
Classifier: Development Status :: 3 - Alpha
Classifier: Environment :: Console
Classifier: Intended Audience :: End Users/Desktop
Classifier: License :: OSI Approved :: MIT License
Classifier: Operating System :: OS Independent
Classifier: Programming Language :: Python :: 3
Classifier: Programming Language :: Python :: 3.9
Classifier: Programming Language :: Python :: 3.10
Classifier: Programming Language :: Python :: 3.11
Classifier: Topic :: Office/Business :: Scheduling
Classifier: Topic :: Utilities
Requires-Python: >=3.9
License-File: LICENSE
Requires-Dist: aiohappyeyeballs
Requires-Dist: aiohttp
Requires-Dist: aiohttp-jinja2
Requires-Dist: aiosignal
Requires-Dist: anyio
Requires-Dist: arrow
Requires-Dist: attrs
Requires-Dist: build
Requires-Dist: bs4
Requires-Dist: caldav
Requires-Dist: canvasapi
Requires-Dist: certifi
Requires-Dist: charset-normalizer
Requires-Dist: click
Requires-Dist: docutils
Requires-Dist: frozenlist
Requires-Dist: h11
Requires-Dist: httpcore
Requires-Dist: httpx
Requires-Dist: icalendar
Requires-Dist: idna
Requires-Dist: jaraco.classes
Requires-Dist: jaraco.context
Requires-Dist: jaraco.functools
Requires-Dist: Jinja2
Requires-Dist: keyring
Requires-Dist: linkify-it-py
Requires-Dist: lxml
Requires-Dist: markdown-it-py
Requires-Dist: MarkupSafe
Requires-Dist: mdit-py-plugins
Requires-Dist: mdurl
Requires-Dist: more-itertools
Requires-Dist: msgpack
Requires-Dist: multidict
Requires-Dist: nh3
Requires-Dist: packaging
Requires-Dist: pkginfo
Requires-Dist: platformdirs
Requires-Dist: propcache
Requires-Dist: psutil
Requires-Dist: pyfiglet
Requires-Dist: Pygments
Requires-Dist: pyproject_hooks
Requires-Dist: python-dateutil
Requires-Dist: python-dotenv
Requires-Dist: pytz
Requires-Dist: readme_renderer
Requires-Dist: recurring-ical-events
Requires-Dist: redis
Requires-Dist: requests
Requires-Dist: requests-toolbelt
Requires-Dist: rfc3986
Requires-Dist: rich
Requires-Dist: six
Requires-Dist: sniffio
Requires-Dist: spotipy
Requires-Dist: textual>=2.1.1
Requires-Dist: textual[syntax]
Requires-Dist: textual-serve
Requires-Dist: tree-sitter
Requires-Dist: tree-sitter-bash
Requires-Dist: tree-sitter-css
Requires-Dist: tree-sitter-go
Requires-Dist: tree-sitter-html
Requires-Dist: tree-sitter-java
Requires-Dist: tree-sitter-javascript<0.24.0,>=0.23.0
Requires-Dist: tree-sitter-json<0.25.0,>=0.24.0
Requires-Dist: tree-sitter-python
Requires-Dist: tree-sitter-regex
Requires-Dist: tree-sitter-rust
Requires-Dist: tree-sitter-sql
Requires-Dist: tree-sitter-toml
Requires-Dist: tree-sitter-xml
Requires-Dist: tree-sitter-yaml
Requires-Dist: twine
Requires-Dist: types-python-dateutil
Requires-Dist: typing_extensions
Requires-Dist: tzdata
Requires-Dist: uc-micro-py
Requires-Dist: urllib3
Requires-Dist: vobject
Requires-Dist: x-wr-timezone
Requires-Dist: yarl
Requires-Dist: jedi
Requires-Dist: send2trash
Provides-Extra: test
Requires-Dist: pytest>=7.0.0; extra == "test"
Requires-Dist: pytest-asyncio>=0.21.0; extra == "test"
Requires-Dist: pytest-cov>=4.1.0; extra == "test"
Requires-Dist: pytest-mock>=3.11.1; extra == "test"
Dynamic: license-file
